date_location_extractor
