Metadata-Version: 2.1
Name: date-location-extractor
Version: 0.1.1
Summary: Extract date and location from a list of strings
Home-page: https://github.com/elitepc/date_location_extractor
Author: elitepc
Author-email: 
License: MIT
Platform: UNKNOWN
Classifier: License :: OSI Approved :: MIT License
Classifier: Programming Language :: Python
Classifier: Programming Language :: Python :: 3
